{
    "pCASL_PLD1800":[
        "asl",
        "acq-pcasl_task-rest_asl",
        "UNASSIGNED"
    ],
    "T2_FLAIR":[
        "anat",
        "FLAIR",
        "UNASSIGNED"
    ],
    "AAHead_Scout":[
        "EXCLUDE_BIDS_Directory",
        "EXCLUDE_BIDS_Name",
        "UNASSIGNED"
    ],
    "DMRI-3Shell-MB-RPE":[
        "misc",
        "acq-rpe_dwi",
        "UNASSIGNED"
    ],
    "MoCoSeries":[
        "func",
        "acq-moco_task-rest_bold",
        "UNASSIGNED"
    ],
    "Perfusion_Weighted":[
        "asl",
        "acq-perfwt_task-rest_asl",
        "UNASSIGNED"
    ],
    "RS-FMRI-MB-high_resolution":[
        "func",
        "acq-std_task-rest_bold",
        "UNASSIGNED"
    ],
    "T1-MPRAGE_ND":[
        "anat",
        "acq-nd_T1w",
        "UNASSIGNED"
    ],
    "DMRI-3Shell-MB":[
        "dwi",
        "dwi",
        "UNASSIGNED"
    ],
    "T1-MPRAGE":[
        "anat",
        "acq-std_T1w",
        "UNASSIGNED"
    ],
    "AAHead_Scout_MPR_tra":[
        "EXCLUDE_BIDS_Directory",
        "EXCLUDE_BIDS_Name",
        "UNASSIGNED"
    ],
    "AAHead_Scout_MPR_cor":[
        "EXCLUDE_BIDS_Directory",
        "EXCLUDE_BIDS_Name",
        "UNASSIGNED"
    ],
    "AAHead_Scout_MPR_sag":[
        "EXCLUDE_BIDS_Directory",
        "EXCLUDE_BIDS_Name",
        "UNASSIGNED"
    ],
    "JJWANGS_pCASL_PLD1800_K_TEST_5_15_2018":[
        "asl",
        "acq-pcasl-jjwang_task-rest_asl",
        "UNASSIGNED"
    ],
    "3D-ASL":[
        "asl",
        "acq-3d_task-rest_asl",
        "UNASSIGNED"
    ],
    "pd+t2_tse_tra_3mm":[
        "anat",
        "T2w",
        "UNASSIGNED"
    ],
    "TOF_3D_multi-slab_MIP_COR":[
        "anat",
        "acq-cor_mip",
        "UNASSIGNED"
    ],
    "TOF_3D_multi-slab_MIP_TRA":[
        "anat",
        "acq-tra_mip",
        "UNASSIGNED"
    ],
    "TOF_3D_multi-slab":[
        "anat",
        "angio",
        "UNASSIGNED"
    ],
    "TOF_3D_multi-slab_MIP_SAG":[
        "anat",
        "acq-sag_mip",
        "UNASSIGNED"
    ],
    "petra":[
        "anat",
        "acq-petra_T1w",
        "UNASSIGNED"
    ],
    "localizer_S14_DIS2D":[
        "EXCLUDE_BIDS_Directory",
        "EXCLUDE_BIDS_Name",
        "UNASSIGNED"
    ],
    "localizer":[
        "EXCLUDE_BIDS_Directory",
        "EXCLUDE_BIDS_Name",
        "UNASSIGNED"
    ],
    "ep2d_diff_mddw_20_p2_TRACEW":[
        "misc",
        "trace",
        "UNASSIGNED"
    ],
    "ep2d_diff_mddw_20_p2_ColFA":[
        "misc",
        "colFA",
        "UNASSIGNED"
    ],
    "ep2d_diff_mddw_20_p2_ADC":[
        "misc",
        "adc",
        "UNASSIGNED"
    ],
    "JJWANGS_PCASL":[
        "asl",
        "acq-pcasl-jjwang_task-rest_asl",
        "UNASSIGNED"
    ],
    "ep2d_diff_mddw_20_p2":[
        "dwi",
        "dwi",
        "UNASSIGNED"
    ],
    "ep2d_diff_mddw_20_p2_FA":[
        "misc",
        "fa",
        "UNASSIGNED"
    ],    
    "ep2d_diff_mddw_RPE":[
        "misc",
        "acq-rpe_dwi",
        "UNASSIGNED"
    ],
    "DTI_MB_3SHELL_ColFA":[
        "misc",
        "colFA",
        "UNASSIGNED"
    ],
    "DTI_MB_3SHELL_ADC":[
        "misc",
        "adc",
        "UNASSIGNED"
    ],
    "DTI_MB_3SHELL":[
        "dwi",
        "dwi",
        "UNASSIGNED"
    ],
    "DTI_MB_3SHELL_TRACEW":[
        "misc",
        "trace",
        "UNASSIGNED"
    ],
    "DTI_MB_3SHELL_FA":[
        "misc",
        "fa",
        "UNASSIGNED"
    ],
    "DTI_MB_3SHELL_RPE":[
        "misc",
        "acq-rpe_dwi",
        "UNASSIGNED"
    ]

}
